azure/ai/vision/face/__init__.py
azure/ai/vision/face/_client.py
azure/ai/vision/face/_configuration.py
azure/ai/vision/face/_model_base.py
azure/ai/vision/face/_patch.py
azure/ai/vision/face/_serialization.py
azure/ai/vision/face/_validation.py
azure/ai/vision/face/_vendor.py
azure/ai/vision/face/_version.py
azure/ai/vision/face/py.typed
azure/ai/vision/face/aio/__init__.py
azure/ai/vision/face/aio/_client.py
azure/ai/vision/face/aio/_configuration.py
azure/ai/vision/face/aio/_patch.py
azure/ai/vision/face/aio/_vendor.py
azure/ai/vision/face/aio/operations/__init__.py
azure/ai/vision/face/aio/operations/_operations.py
azure/ai/vision/face/aio/operations/_patch.py
azure/ai/vision/face/models/__init__.py
azure/ai/vision/face/models/_enums.py
azure/ai/vision/face/models/_models.py
azure/ai/vision/face/models/_patch.py
azure/ai/vision/face/operations/__init__.py
azure/ai/vision/face/operations/_operations.py
azure/ai/vision/face/operations/_patch.py
azure_ai_vision_face-1.0.0b2.dist-info/LICENSE
azure_ai_vision_face-1.0.0b2.dist-info/METADATA
azure_ai_vision_face-1.0.0b2.dist-info/WHEEL
azure_ai_vision_face-1.0.0b2.dist-info/top_level.txt
azure_ai_vision_face-1.0.0b2.dist-info/RECORD
